wyn_pm/__init__.py
wyn_pm/efficient_portfolio.py
wyn_pm/stock_analyzer.py
wyn_pm/trainer.py
wyn_pm-0.2.9.dist-info/METADATA
wyn_pm-0.2.9.dist-info/WHEEL
wyn_pm-0.2.9.dist-info/RECORD
