Metadata-Version: 2.1
Name: wyn-pm
Version: 0.2.9
Summary: The library helps analysts to investigate portfolio and stock market.
Author: Yiqiao Yin
Author-email: yiqiao.yin@wyn-associates.com
Requires-Python: >=3.9,<4.0
Classifier: Programming Language :: Python :: 3
Classifier: Programming Language :: Python :: 3.9
Classifier: Programming Language :: Python :: 3.10
Classifier: Programming Language :: Python :: 3.11
Classifier: Programming Language :: Python :: 3.12
Requires-Dist: numpy (>=1.21.6)
Requires-Dist: pandas (>=2.2.2,<3.0.0)
Requires-Dist: plotly (>=5.22.0,<6.0.0)
Requires-Dist: prettytable (>=3.10.0,<4.0.0)
Requires-Dist: scikit-learn (>=1.5.0,<2.0.0)
Requires-Dist: scipy (==1.11.4)
Requires-Dist: tensorflow (>=2.15.0,<3.0.0)
Requires-Dist: yfinance (>=0.2.40,<0.3.0)
